[
    {
        "child_count": 3,
        "display_string": "A. Books",
        "jsonmodel_type": "archival_object",
        "level": "file",
        "parent_id": 1749901,
        "parsed_title": "A. Books",
        "position": 0,
        "title": "A. Books",
        "uri": "/repositories/12/archival_objects/1749902",
        "waypoint_size": 200,
        "waypoints": 1
    },
    {
        "child_count": 9,
        "display_string": "B. Forwards, Prefaces, etc. (in chronological order)",
        "jsonmodel_type": "archival_object",
        "level": "file",
        "parent_id": 1749901,
        "parsed_title": "B. Forwards, Prefaces, etc. (in chronological order)",
        "position": 1,
        "title": "B. Forwards, Prefaces, etc. (in chronological order)",
        "uri": "/repositories/12/archival_objects/1749912",
        "waypoint_size": 200,
        "waypoints": 1
    },
    {
        "child_count": 63,
        "display_string": "C. Articles for Journals and Periodicals (arranged alphabetically by title)",
        "jsonmodel_type": "archival_object",
        "level": "file",
        "parent_id": 1749901,
        "parsed_title": "C. Articles for Journals and Periodicals (arranged alphabetically by title)",
        "position": 2,
        "title": "C. Articles for Journals and Periodicals (arranged alphabetically by title)",
        "uri": "/repositories/12/archival_objects/1749922",
        "waypoint_size": 200,
        "waypoints": 1
    },
    {
        "child_count": 6,
        "display_string": "D. Miscellaneous Articles and Essays (arranged alphabetically by title)",
        "jsonmodel_type": "archival_object",
        "level": "file",
        "parent_id": 1749901,
        "parsed_title": "D. Miscellaneous Articles and Essays (arranged alphabetically by title)",
        "position": 3,
        "title": "D. Miscellaneous Articles and Essays (arranged alphabetically by title)",
        "uri": "/repositories/12/archival_objects/1749986",
        "waypoint_size": 200,
        "waypoints": 1
    },
    {
        "child_count": 19,
        "display_string": "E. Syndicated Newspaper Articles (1920-1922) (miscellaneous drafts and clippings)",
        "jsonmodel_type": "archival_object",
        "level": "file",
        "parent_id": 1749901,
        "parsed_title": "E. Syndicated Newspaper Articles (1920-1922) (miscellaneous drafts and clippings)",
        "position": 4,
        "title": "E. Syndicated Newspaper Articles (1920-1922) (miscellaneous drafts and clippings)",
        "uri": "/repositories/12/archival_objects/1749993",
        "waypoint_size": 200,
        "waypoints": 1
    },
    {
        "child_count": 2,
        "display_string": "F. Occasional Pieces",
        "jsonmodel_type": "archival_object",
        "level": "file",
        "parent_id": 1749901,
        "parsed_title": "F. Occasional Pieces",
        "position": 5,
        "title": "F. Occasional Pieces",
        "uri": "/repositories/12/archival_objects/1750013",
        "waypoint_size": 200,
        "waypoints": 1
    },
    {
        "child_count": 2,
        "display_string": "G. Miscellaneous Items",
        "jsonmodel_type": "archival_object",
        "level": "file",
        "parent_id": 1749901,
        "parsed_title": "G. Miscellaneous Items",
        "position": 6,
        "title": "G. Miscellaneous Items",
        "uri": "/repositories/12/archival_objects/1750063",
        "waypoint_size": 200,
        "waypoints": 1
    }
]