{"agent_representation": {"ref": "/agents/corporate_entities/14145"},
 "country": "AT",
 "create_time": "2021-07-28T17:32:13Z",
 "created_by": "amd243",
 "description": "Repository description",
 "display_string": "Test repository (TEST_REPO_NAME)",
 "image_url": "https://j",
 "is_slug_auto": false,
 "jsonmodel_type": "repository",
 "last_modified_by": "amd243",
 "location": {"access_information": "Repository access information",
              "address_1": "Repo address 1",
              "address_2": "Repo address 2",
              "address_3": "Repo address 3",
              "city": "Repo city",
              "country": "Repo country",
              "create_time": "2021-07-28T17:32:14Z",
              "created_by": "amd243",
              "jsonmodel_type": "repository_location",
              "last_modified_by": "amd243",
              "latitude": "41.3103075",
              "libcal_id": "libcall identifier",
              "lock_version": 0,
              "longitude": "-72.9367107",
              "post_code": "Repo post code",
              "region": "Repo state",
              "system_mtime": "2021-07-28T17:32:14Z",
              "user_mtime": "2021-07-28T17:32:14Z"},
 "lock_version": 0,
 "name": "Test repository",
 "oai_is_disabled": false,
 "oai_sets_available": "[]",
 "org_code": "Organization code",
 "parent_institution_name": "Yale University",
 "publish": true,
 "repo_code": "TEST_REPO_NAME",
 "slug": "test_repo_name",
 "system_mtime": "2021-07-28T17:32:13Z",
 "uri": "/repositories/19",
 "url": "https://j",
 "user_mtime": "2021-07-28T17:32:13Z"}